{
	"description": "项目配置文件",
	"packOptions": {
		"ignore": []
	},
	"setting": {
		"urlCheck": true,
		"es6": true,
		"postcss": true,
		"minified": true,
		"newFeature": true,
		"nodeModules": true,
		"autoAudits": false,
		"uglifyFileName": true
	},
	"compileType": "miniprogram",
	"libVersion": "2.6.1",
	"appid": "wx9fa47d9522cc0237",
	"projectname": "%E7%9B%B8%E4%BA%B2%E5%B0%8F%E7%BA%A2%E5%9C%88",
	"debugOptions": {
		"hidedInDevtools": []
	},
	"scripts": {},
	"condition": {
		"search": {
			"current": -1,
			"list": []
		},
		"conversation": {
			"current": -1,
			"list": []
		},
		"plugin": {
			"current": -1,
			"list": []
		},
		"game": {
			"list": []
		},
		"miniprogram": {
			"current": 3,
			"list": [
				{
					"id": -1,
					"name": "圈子介绍页",
					"pathName": "pages/circle-introduce/circle-introduce",
					"query": "circleId=10",
					"scene": null
				},
				{
					"id": 1,
					"name": "上海相亲群",
					"pathName": "pages/circle-dynamic/circle-dynamic",
					"query": "circleId=30&navTitle=上海相亲群",
					"scene": null
				},
				{
					"id": 2,
					"name": "我的动态",
					"pathName": "pages/dynamic/dynamic",
					"query": "userId=3061",
					"scene": null
				},
				{
					"id": 3,
					"name": "圈子介绍",
					"pathName": "pages/circle-introduce/circle-introduce",
					"query": "circleId=74",
					"scene": null
				}
			]
		}
	}
}